AUTHORS.rst
CONTRIBUTING.rst
HISTORY.rst
LICENSE
MANIFEST.in
README.rst
setup.cfg
setup.py
docs/Makefile
docs/authors.rst
docs/conf.py
docs/contributing.rst
docs/history.rst
docs/index.rst
docs/installation.rst
docs/make.bat
docs/readme.rst
docs/usage.rst
ktm/__init__.py
ktm/ktm.py
ktm.egg-info/PKG-INFO
ktm.egg-info/SOURCES.txt
ktm.egg-info/dependency_links.txt
ktm.egg-info/not-zip-safe
ktm.egg-info/top_level.txt
tests/__init__.py
tests/test_ktm.py