Metadata-Version: 1.1
Name: ktm
Version: 0.1.1
Summary: Configurable notification daemon with queues and history display
Home-page: https://github.com/skalanux/ktm
Author: Juan Manuel Schillaci
Author-email: jmschillaci@gmail.com
License: GPLv3+
Keywords: ktm
Platform: UNKNOWN
Classifier: Development Status :: 2 - Pre-Alpha
Classifier: Intended Audience :: Developers
Classifier: License :: OSI Approved :: GNU General Public License v3 or later (GPLv3+)
Classifier: Natural Language :: English
Classifier: Programming Language :: Python :: 2
Classifier: Programming Language :: Python :: 2.6
Classifier: Programming Language :: Python :: 2.7
Classifier: Programming Language :: Python :: 3
Classifier: Programming Language :: Python :: 3.3
Classifier: Programming Language :: Python :: 3.4
